{
  "version": 1,
  "entries": [
    {
      "rank": 2101,
      "word": "alter",
      "pos": "noun",
      "ipa_strong": "/ɔltɜr/",
      "example_sentence": "The alter is very good.",
      "cefr_level": "C1"
    },
    {
      "rank": 2102,
      "word": "perceive",
      "pos": "noun",
      "ipa_strong": "/pɜrsiːv/",
      "example_sentence": "The perceive is very good.",
      "cefr_level": "C1"
    },
    {
      "rank": 2103,
      "word": "routine",
      "pos": "noun",
      "ipa_strong": "/ɹuːtiːn/",
      "example_sentence": "The routine is very good.",
      "cefr_level": "C1"
    },
    {
      "rank": 2104,
      "word": "sink",
      "pos": "noun",
      "ipa_strong": "/sɪŋk/",
      "example_sentence": "The sink is very good.",
      "cefr_level": "C1"
    },
    {
      "rank": 2105,
      "word": "stare",
      "pos": "noun",
      "ipa_strong": "/stɛɹ/",
      "example_sentence": "The stare is very good.",
      "cefr_level": "C1"
    },
    {
      "rank": 2106,
      "word": "anymore",
      "pos": "noun",
      "ipa_strong": "/ɛniːmɔɹ/",
      "example_sentence": "The anymore is very good.",
      "cefr_level": "C1"
    },
    {
      "rank": 2107,
      "word": "hero",
      "pos": "noun",
      "ipa_strong": "/hɪɹoʊ/",
      "example_sentence": "The hero is very good.",
      "cefr_level": "C1"
    },
    {
      "rank": 2108,
      "word": "supporter",
      "pos": "noun",
      "ipa_strong": "/sʌpɔɹtɜr/",
      "example_sentence": "The supporter is very good.",
      "cefr_level": "C1"
    },
    {
      "rank": 2109,
      "word": "convert",
      "pos": "noun",
      "ipa_strong": "/kɑnvɜrt/",
      "example_sentence": "The convert is very good.",
      "cefr_level": "C1"
    },
    {
      "rank": 2110,
      "word": "steady",
      "pos": "noun",
      "ipa_strong": "/stɛdiː/",
      "example_sentence": "The steady is very good.",
      "cefr_level": "C1"
    },
    {
      "rank": 2111,
      "word": "meter",
      "pos": "noun",
      "ipa_strong": "/miːtɜr/",
      "example_sentence": "The meter is very good.",
      "cefr_level": "C1"
    },
    {
      "rank": 2112,
      "word": "truck",
      "pos": "noun",
      "ipa_strong": "/tɹʌk/",
      "example_sentence": "The truck is very good.",
      "cefr_level": "C1"
    },
    {
      "rank": 2113,
      "word": "nose",
      "pos": "noun",
      "ipa_strong": "/noʊz/",
      "example_sentence": "The nose is very good.",
      "cefr_level": "C1"
    },
    {
      "rank": 2114,
      "word": "beside",
      "pos": "preposition",
      "ipa_strong": "/bɪsaɪd/",
      "example_sentence": "It is beside the box now.",
      "cefr_level": "C1"
    },
    {
      "rank": 2115,
      "word": "sail",
      "pos": "noun",
      "ipa_strong": "/seɪl/",
      "example_sentence": "The sail is very good.",
      "cefr_level": "C1"
    },
    {
      "rank": 2116,
      "word": "disaster",
      "pos": "noun",
      "ipa_strong": "/dɪzæstɜr/",
      "example_sentence": "The disaster is very good.",
      "cefr_level": "C1"
    },
    {
      "rank": 2117,
      "word": "pace",
      "pos": "noun",
      "ipa_strong": "/peɪs/",
      "example_sentence": "The pace is very good.",
      "cefr_level": "C1"
    },
    {
      "rank": 2118,
      "word": "heavily",
      "pos": "noun",
      "ipa_strong": "/hɛvʌliː/",
      "example_sentence": "The heavily is very good.",
      "cefr_level": "C1"
    },
    {
      "rank": 2119,
      "word": "devote",
      "pos": "noun",
      "ipa_strong": "/dɪvoʊt/",
      "example_sentence": "The devote is very good.",
      "cefr_level": "C1"
    },
    {
      "rank": 2120,
      "word": "terrorist",
      "pos": "noun",
      "ipa_strong": "/tɛɹɜrɪst/",
      "example_sentence": "The terrorist is very good.",
      "cefr_level": "C1"
    },
    {
      "rank": 2121,
      "word": "justify",
      "pos": "verb",
      "ipa_strong": "/dʒʌstʌfaɪ/",
      "example_sentence": "I justify every day here.",
      "cefr_level": "C1"
    },
    {
      "rank": 2122,
      "word": "vital",
      "pos": "noun",
      "ipa_strong": "/vaɪtʌl/",
      "example_sentence": "The vital is very good.",
      "cefr_level": "C1"
    },
    {
      "rank": 2123,
      "word": "fascinate",
      "pos": "noun",
      "ipa_strong": "/fæsʌneɪt/",
      "example_sentence": "The fascinate is very good.",
      "cefr_level": "C1"
    },
    {
      "rank": 2124,
      "word": "external",
      "pos": "adjective",
      "ipa_strong": "/ɪkstɜrnʌl/",
      "example_sentence": "It is very external today.",
      "cefr_level": "C1"
    },
    {
      "rank": 2125,
      "word": "spare",
      "pos": "noun",
      "ipa_strong": "/spɛɹ/",
      "example_sentence": "The spare is very good.",
      "cefr_level": "C1"
    },
    {
      "rank": 2126,
      "word": "whenever",
      "pos": "noun",
      "ipa_strong": "/wɛnɛvɜr/",
      "example_sentence": "The whenever is very good.",
      "cefr_level": "C1"
    },
    {
      "rank": 2127,
      "word": "depression",
      "pos": "noun",
      "ipa_strong": "/dɪpɹɛʃʌn/",
      "example_sentence": "The depression is very good.",
      "cefr_level": "C1"
    },
    {
      "rank": 2128,
      "word": "guilty",
      "pos": "noun",
      "ipa_strong": "/ɡɪltiː/",
      "example_sentence": "The guilty is very good.",
      "cefr_level": "C1"
    },
    {
      "rank": 2129,
      "word": "underlie",
      "pos": "noun",
      "ipa_strong": "/ʌndɜrlaɪ/",
      "example_sentence": "The underlie is very good.",
      "cefr_level": "C1"
    },
    {
      "rank": 2130,
      "word": "mom",
      "pos": "noun",
      "ipa_strong": "/mɑm/",
      "example_sentence": "The mom is very good.",
      "cefr_level": "C1"
    },
    {
      "rank": 2131,
      "word": "distinction",
      "pos": "noun",
      "ipa_strong": "/dɪstɪŋkʃʌn/",
      "example_sentence": "The distinction is very good.",
      "cefr_level": "C1"
    },
    {
      "rank": 2132,
      "word": "satisfaction",
      "pos": "noun",
      "ipa_strong": "/sætʌsfækʃʌn/",
      "example_sentence": "The satisfaction is very good.",
      "cefr_level": "C1"
    },
    {
      "rank": 2133,
      "word": "incorporate",
      "pos": "noun",
      "ipa_strong": "/ɪnkɔɹpɜreɪt/",
      "example_sentence": "The incorporate is very good.",
      "cefr_level": "C1"
    },
    {
      "rank": 2134,
      "word": "pour",
      "pos": "noun",
      "ipa_strong": "/pɔɹ/",
      "example_sentence": "The pour is very good.",
      "cefr_level": "C1"
    },
    {
      "rank": 2135,
      "word": "sweep",
      "pos": "noun",
      "ipa_strong": "/swiːp/",
      "example_sentence": "The sweep is very good.",
      "cefr_level": "C1"
    },
    {
      "rank": 2136,
      "word": "obligation",
      "pos": "noun",
      "ipa_strong": "/ɑblʌɡeɪʃʌn/",
      "example_sentence": "The obligation is very good.",
      "cefr_level": "C1"
    },
    {
      "rank": 2137,
      "word": "sir",
      "pos": "noun",
      "ipa_strong": "/sɜr/",
      "example_sentence": "The sir is very good.",
      "cefr_level": "C1"
    },
    {
      "rank": 2138,
      "word": "evaluate",
      "pos": "noun",
      "ipa_strong": "/ɪvæljuːeɪt/",
      "example_sentence": "The evaluate is very good.",
      "cefr_level": "C1"
    },
    {
      "rank": 2139,
      "word": "anger",
      "pos": "noun",
      "ipa_strong": "/æŋɡɜr/",
      "example_sentence": "The anger is very good.",
      "cefr_level": "C1"
    },
    {
      "rank": 2140,
      "word": "pub",
      "pos": "noun",
      "ipa_strong": "/pʌb/",
      "example_sentence": "The pub is very good.",
      "cefr_level": "C1"
    },
    {
      "rank": 2141,
      "word": "perception",
      "pos": "noun",
      "ipa_strong": "/pɜrsɛpʃʌn/",
      "example_sentence": "The perception is very good.",
      "cefr_level": "C1"
    },
    {
      "rank": 2142,
      "word": "naturally",
      "pos": "noun",
      "ipa_strong": "/nætʃɜrʌliː/",
      "example_sentence": "The naturally is very good.",
      "cefr_level": "C1"
    },
    {
      "rank": 2143,
      "word": "currency",
      "pos": "noun",
      "ipa_strong": "/kɜrʌnsiː/",
      "example_sentence": "The currency is very good.",
      "cefr_level": "C1"
    },
    {
      "rank": 2144,
      "word": "database",
      "pos": "noun",
      "ipa_strong": "/deɪtʌbeɪs/",
      "example_sentence": "The database is very good.",
      "cefr_level": "C1"
    },
    {
      "rank": 2145,
      "word": "initially",
      "pos": "noun",
      "ipa_strong": "/ɪnɪʃʌliː/",
      "example_sentence": "The initially is very good.",
      "cefr_level": "C1"
    },
    {
      "rank": 2146,
      "word": "territory",
      "pos": "noun",
      "ipa_strong": "/tɛɹɪtɔɹiː/",
      "example_sentence": "The territory is very good.",
      "cefr_level": "C1"
    },
    {
      "rank": 2147,
      "word": "stream",
      "pos": "noun",
      "ipa_strong": "/stɹiːm/",
      "example_sentence": "The stream is very good.",
      "cefr_level": "C1"
    },
    {
      "rank": 2148,
      "word": "rarely",
      "pos": "noun",
      "ipa_strong": "/ɹɛɹliː/",
      "example_sentence": "The rarely is very good.",
      "cefr_level": "C1"
    },
    {
      "rank": 2149,
      "word": "height",
      "pos": "noun",
      "ipa_strong": "/haɪt/",
      "example_sentence": "The height is very good.",
      "cefr_level": "C1"
    },
    {
      "rank": 2150,
      "word": "apparent",
      "pos": "noun",
      "ipa_strong": "/ʌpɛɹʌnt/",
      "example_sentence": "The apparent is very good.",
      "cefr_level": "C1"
    },
    {
      "rank": 2151,
      "word": "western",
      "pos": "adjective",
      "ipa_strong": "/wɛstɜrn/",
      "example_sentence": "It is very western today.",
      "cefr_level": "C1"
    },
    {
      "rank": 2152,
      "word": "expansion",
      "pos": "noun",
      "ipa_strong": "/ɪkspænʃʌn/",
      "example_sentence": "The expansion is very good.",
      "cefr_level": "C1"
    },
    {
      "rank": 2153,
      "word": "constantly",
      "pos": "noun",
      "ipa_strong": "/kɑnstʌntliː/",
      "example_sentence": "The constantly is very good.",
      "cefr_level": "C1"
    },
    {
      "rank": 2154,
      "word": "muscle",
      "pos": "noun",
      "ipa_strong": "/mʌsʌl/",
      "example_sentence": "The muscle is very good.",
      "cefr_level": "C1"
    },
    {
      "rank": 2155,
      "word": "scare",
      "pos": "noun",
      "ipa_strong": "/skɛɹ/",
      "example_sentence": "The scare is very good.",
      "cefr_level": "C1"
    },
    {
      "rank": 2156,
      "word": "badly",
      "pos": "noun",
      "ipa_strong": "/bædliː/",
      "example_sentence": "The badly is very good.",
      "cefr_level": "C1"
    },
    {
      "rank": 2157,
      "word": "everyday",
      "pos": "noun",
      "ipa_strong": "/ɛvɹiːdeɪ/",
      "example_sentence": "The everyday is very good.",
      "cefr_level": "C1"
    },
    {
      "rank": 2158,
      "word": "boundary",
      "pos": "noun",
      "ipa_strong": "/baʊndɜriː/",
      "example_sentence": "The boundary is very good.",
      "cefr_level": "C1"
    },
    {
      "rank": 2159,
      "word": "ratio",
      "pos": "noun",
      "ipa_strong": "/ɹeɪʃiːoʊ/",
      "example_sentence": "The ratio is very good.",
      "cefr_level": "C1"
    },
    {
      "rank": 2160,
      "word": "essay",
      "pos": "noun",
      "ipa_strong": "/ɛseɪ/",
      "example_sentence": "The essay is very good.",
      "cefr_level": "C1"
    },
    {
      "rank": 2161,
      "word": "scream",
      "pos": "noun",
      "ipa_strong": "/skɹiːm/",
      "example_sentence": "The scream is very good.",
      "cefr_level": "C1"
    },
    {
      "rank": 2162,
      "word": "withdraw",
      "pos": "noun",
      "ipa_strong": "/wɪðdɹɔ/",
      "example_sentence": "The withdraw is very good.",
      "cefr_level": "C1"
    },
    {
      "rank": 2163,
      "word": "pollution",
      "pos": "noun",
      "ipa_strong": "/pʌluːʃʌn/",
      "example_sentence": "The pollution is very good.",
      "cefr_level": "C1"
    },
    {
      "rank": 2164,
      "word": "disorder",
      "pos": "noun",
      "ipa_strong": "/dɪsɔɹdɜr/",
      "example_sentence": "The disorder is very good.",
      "cefr_level": "C1"
    },
    {
      "rank": 2165,
      "word": "furniture",
      "pos": "noun",
      "ipa_strong": "/fɜrnɪtʃɜr/",
      "example_sentence": "The furniture is very good.",
      "cefr_level": "C1"
    },
    {
      "rank": 2166,
      "word": "symbol",
      "pos": "noun",
      "ipa_strong": "/sɪmbʌl/",
      "example_sentence": "The symbol is very good.",
      "cefr_level": "C1"
    },
    {
      "rank": 2167,
      "word": "apartment",
      "pos": "noun",
      "ipa_strong": "/ʌpɑɹtmʌnt/",
      "example_sentence": "The apartment is very good.",
      "cefr_level": "C1"
    },
    {
      "rank": 2168,
      "word": "demonstration",
      "pos": "noun",
      "ipa_strong": "/dɛmʌnstɹeɪʃʌn/",
      "example_sentence": "The demonstration is very good.",
      "cefr_level": "C1"
    },
    {
      "rank": 2169,
      "word": "analyst",
      "pos": "noun",
      "ipa_strong": "/ænʌlɪst/",
      "example_sentence": "The analyst is very good.",
      "cefr_level": "C1"
    },
    {
      "rank": 2170,
      "word": "platform",
      "pos": "noun",
      "ipa_strong": "/plætfɔɹm/",
      "example_sentence": "The platform is very good.",
      "cefr_level": "C1"
    },
    {
      "rank": 2171,
      "word": "steel",
      "pos": "noun",
      "ipa_strong": "/stiːl/",
      "example_sentence": "The steel is very good.",
      "cefr_level": "C1"
    },
    {
      "rank": 2172,
      "word": "cake",
      "pos": "noun",
      "ipa_strong": "/keɪk/",
      "example_sentence": "The cake is very good.",
      "cefr_level": "C1"
    },
    {
      "rank": 2173,
      "word": "transform",
      "pos": "noun",
      "ipa_strong": "/tɹænsfɔɹm/",
      "example_sentence": "The transform is very good.",
      "cefr_level": "C1"
    },
    {
      "rank": 2174,
      "word": "wound",
      "pos": "noun",
      "ipa_strong": "/waʊnd/",
      "example_sentence": "The wound is very good.",
      "cefr_level": "C1"
    },
    {
      "rank": 2175,
      "word": "restriction",
      "pos": "noun",
      "ipa_strong": "/ɹiːstɹɪkʃʌn/",
      "example_sentence": "The restriction is very good.",
      "cefr_level": "C1"
    },
    {
      "rank": 2176,
      "word": "foundation",
      "pos": "noun",
      "ipa_strong": "/faʊndeɪʃʌn/",
      "example_sentence": "The foundation is very good.",
      "cefr_level": "C1"
    },
    {
      "rank": 2177,
      "word": "designer",
      "pos": "noun",
      "ipa_strong": "/dɪzaɪnɜr/",
      "example_sentence": "The designer is very good.",
      "cefr_level": "C1"
    },
    {
      "rank": 2178,
      "word": "strain",
      "pos": "noun",
      "ipa_strong": "/stɹeɪn/",
      "example_sentence": "The strain is very good.",
      "cefr_level": "C1"
    },
    {
      "rank": 2179,
      "word": "innovation",
      "pos": "noun",
      "ipa_strong": "/ɪnʌveɪʃʌn/",
      "example_sentence": "The innovation is very good.",
      "cefr_level": "C1"
    },
    {
      "rank": 2180,
      "word": "album",
      "pos": "noun",
      "ipa_strong": "/ælbʌm/",
      "example_sentence": "The album is very good.",
      "cefr_level": "C1"
    },
    {
      "rank": 2181,
      "word": "singer",
      "pos": "noun",
      "ipa_strong": "/sɪŋɜr/",
      "example_sentence": "The singer is very good.",
      "cefr_level": "C1"
    },
    {
      "rank": 2182,
      "word": "trail",
      "pos": "noun",
      "ipa_strong": "/tɹeɪl/",
      "example_sentence": "The trail is very good.",
      "cefr_level": "C1"
    },
    {
      "rank": 2183,
      "word": "trap",
      "pos": "noun",
      "ipa_strong": "/tɹæp/",
      "example_sentence": "The trap is very good.",
      "cefr_level": "C1"
    },
    {
      "rank": 2184,
      "word": "loose",
      "pos": "noun",
      "ipa_strong": "/luːs/",
      "example_sentence": "The loose is very good.",
      "cefr_level": "C1"
    },
    {
      "rank": 2185,
      "word": "extension",
      "pos": "noun",
      "ipa_strong": "/ɪkstɛnʃʌn/",
      "example_sentence": "The extension is very good.",
      "cefr_level": "C1"
    },
    {
      "rank": 2186,
      "word": "wealth",
      "pos": "noun",
      "ipa_strong": "/wɛlθ/",
      "example_sentence": "The wealth is very good.",
      "cefr_level": "C1"
    },
    {
      "rank": 2187,
      "word": "gradually",
      "pos": "noun",
      "ipa_strong": "/ɡɹædʒuːʌliː/",
      "example_sentence": "The gradually is very good.",
      "cefr_level": "C1"
    },
    {
      "rank": 2188,
      "word": "tank",
      "pos": "noun",
      "ipa_strong": "/tæŋk/",
      "example_sentence": "The tank is very good.",
      "cefr_level": "C1"
    },
    {
      "rank": 2189,
      "word": "evil",
      "pos": "noun",
      "ipa_strong": "/iːvʌl/",
      "example_sentence": "The evil is very good.",
      "cefr_level": "C1"
    },
    {
      "rank": 2190,
      "word": "remarkable",
      "pos": "noun",
      "ipa_strong": "/ɹɪmɑɹkʌbʌl/",
      "example_sentence": "The remarkable is very good.",
      "cefr_level": "C1"
    },
    {
      "rank": 2191,
      "word": "tune",
      "pos": "noun",
      "ipa_strong": "/tuːn/",
      "example_sentence": "The tune is very good.",
      "cefr_level": "C1"
    },
    {
      "rank": 2192,
      "word": "grass",
      "pos": "noun",
      "ipa_strong": "/ɡɹæs/",
      "example_sentence": "The grass is very good.",
      "cefr_level": "C1"
    },
    {
      "rank": 2193,
      "word": "invitation",
      "pos": "noun",
      "ipa_strong": "/ɪnvɪteɪʃʌn/",
      "example_sentence": "The invitation is very good.",
      "cefr_level": "C1"
    },
    {
      "rank": 2194,
      "word": "transition",
      "pos": "noun",
      "ipa_strong": "/tɹænzɪʃʌn/",
      "example_sentence": "The transition is very good.",
      "cefr_level": "C1"
    },
    {
      "rank": 2195,
      "word": "frighten",
      "pos": "noun",
      "ipa_strong": "/fɹaɪtʌn/",
      "example_sentence": "The frighten is very good.",
      "cefr_level": "C1"
    },
    {
      "rank": 2196,
      "word": "bid",
      "pos": "noun",
      "ipa_strong": "/bɪd/",
      "example_sentence": "The bid is very good.",
      "cefr_level": "C1"
    },
    {
      "rank": 2197,
      "word": "breed",
      "pos": "noun",
      "ipa_strong": "/bɹiːd/",
      "example_sentence": "The breed is very good.",
      "cefr_level": "C1"
    },
    {
      "rank": 2198,
      "word": "extraordinary",
      "pos": "noun",
      "ipa_strong": "/ɛkstɹʌɔɹdʌnɛɹiː/",
      "example_sentence": "The extraordinary is very good.",
      "cefr_level": "C1"
    },
    {
      "rank": 2199,
      "word": "brilliant",
      "pos": "noun",
      "ipa_strong": "/bɹɪljʌnt/",
      "example_sentence": "The brilliant is very good.",
      "cefr_level": "C1"
    },
    {
      "rank": 2200,
      "word": "adviser",
      "pos": "noun",
      "ipa_strong": "/ædvaɪzɜr/",
      "example_sentence": "The adviser is very good.",
      "cefr_level": "C1"
    }
  ]
}
